amabase/__init__.py
amabase/__main__.py
amabase/_version.py
amabase/base/admin.py
amabase/base/apps.py
amabase/base/models.py
amabase/base/locale/fr/LC_MESSAGES/django.mo
amabase/base/locale/fr/LC_MESSAGES/django.po
amabase/base/management/seed.py
amabase/base/management/commands/seed.py
amabase/base/migrations/0001_initial.py
amabase/base/migrations/__init__.py
amabase/base/static/base/favicon.ico
amabase/cmdb/admin.py
amabase/cmdb/apps.py
amabase/cmdb/models.py
amabase/cmdb/locale/fr/LC_MESSAGES/django.mo
amabase/cmdb/locale/fr/LC_MESSAGES/django.po
amabase/cmdb/migrations/0001_initial.py
amabase/cmdb/migrations/__init__.py
amabase/conf/__init__.py
amabase/conf/default.py
amabase/conf/exceptions.py
amabase/conf/main.py
amabase/conf/commands/db.py
amabase/conf/commands/settings.py
amabase/conf/internal/db.py
amabase/conf/internal/settings.py
amabase/conf/migrations/0001_init.sql
amabase/django/__init__.py
amabase/django/admin.py
amabase/django/asgi.py
amabase/django/fields.py
amabase/django/urls.py
amabase/ipam/admin.py
amabase/ipam/apps.py
amabase/ipam/models.py
amabase/ipam/locale/fr/LC_MESSAGES/django.mo
amabase/ipam/locale/fr/LC_MESSAGES/django.po
amabase/ipam/migrations/0001_initial.py
amabase/ipam/migrations/__init__.py
amabase/utils/__init__.py
amabase-0.0.1.dist-info/licenses/LICENSE.txt
amabase-0.0.1.dist-info/METADATA
amabase-0.0.1.dist-info/WHEEL
amabase-0.0.1.dist-info/entry_points.txt
amabase-0.0.1.dist-info/top_level.txt
amabase-0.0.1.dist-info/RECORD
