Metadata-Version: 2.4
Name: amabase
Version: 0.0.1
Summary: A simple and flexible asset management application built upon the Django framework. Can also be used as a building block library for more complex applications.
Author-email: Sébastien Hocquet <seb@ipamo.net>
Project-URL: Homepage, https://codeberg.org/ipamo/amabase.git
Project-URL: Bug Tracker, http://codeberg.org/ipamo/amabase/issues
Requires-Python: >=3.9
License-File: LICENSE.txt
Dynamic: license-file
